cybergear/api/MotorLibrary.py
cybergear/api/__init__.py
cybergear/api/__main__.py
cybergear/api/client.py
cybergear/api/device.py
cybergear/api/motor.robot
cybergear/api/server.py
cybergear_api-0.0.1.dist-info/AUTHORS
cybergear_api-0.0.1.dist-info/METADATA
cybergear_api-0.0.1.dist-info/WHEEL
cybergear_api-0.0.1.dist-info/entry_points.txt
cybergear_api-0.0.1.dist-info/pbr.json
cybergear_api-0.0.1.dist-info/top_level.txt
cybergear_api-0.0.1.dist-info/RECORD
